power_rankings/__init__.py
power_rankings/transformations.py
power_rankings-0.1.0.dist-info/LICENSE
power_rankings-0.1.0.dist-info/WHEEL
power_rankings-0.1.0.dist-info/METADATA
power_rankings-0.1.0.dist-info/RECORD
