Metadata-Version: 2.1
Name: power_rankings
Version: 0.1.0
Summary: Power rankings module
Home-page: https://github.com/niesfutbol/power_rankings
Author: NIES
Author-email: nepo@nies.futbol
Requires-Python: >=3.9
Classifier: License :: OSI Approved :: GNU General Public License v3 or later (GPLv3+)
